{
    "person": {
        "id": 123,
        "name": {
            "first": "Julian",
            "second": "Cranfield"
        },
        "dob": "25/04/1968",
        "phoneNumbers": [
            {
                "phone": {
                    "number": "077662223355",
                    "type": "work"
                }
            }
        ],
        "addresses": [
            {
                "address": {
                    "houseNumber": "20",
                    "street": "Post Office Lane",
                    "town": "Redmile",
                    "county": "Notts",
                    "postCode": "NG12 8YU"
                }
            }
        ]
    }
}